datafeed/__init__.py
datafeed/futures/Get_From_Akshare.py
datafeed/futures/__init__.py
datafeed/futures/get_futures_from_local.py
datafeed/macro/Get_From_Ak.py
datafeed/macro/__init__.py
datafeed/macro/currency.py
datafeed/option/__init__.py
datafeed/stock/GetStocksUs.py
datafeed/stock/__init__.py
test/FromSql_Csv.py
test/__init__.py
test/aktest.py
test/baostock.py
test/funtest.py
test/getfutures.py
test/jindutiao.py
test/pklshow.py
test/test.py
test/testqlib.py
test/yh.py
tools/__init__.py
tools/conn.py
tools/fs.py
tools/math.py
tools/str.py
tools/times.py
xdtreader-1.0.3.1.dev3.dist-info/METADATA
xdtreader-1.0.3.1.dev3.dist-info/WHEEL
xdtreader-1.0.3.1.dev3.dist-info/top_level.txt
xdtreader-1.0.3.1.dev3.dist-info/RECORD
