Metadata-Version: 2.1
Name: xdtreader
Version: 1.0.3.1.dev3
Summary: 1234
Home-page: UNKNOWN
Author: iceoryx
Author-email: iceoryx@163.com
License: mit
Platform: UNKNOWN
